metric_time.py
metric_time-1.0.8.dist-info/LICENSE
metric_time-1.0.8.dist-info/METADATA
metric_time-1.0.8.dist-info/WHEEL
metric_time-1.0.8.dist-info/entry_points.txt
metric_time-1.0.8.dist-info/top_level.txt
metric_time-1.0.8.dist-info/RECORD
