Metadata-Version: 2.1
Name: metric-time
Version: 1.0.8
Summary: Implementation of decimal time and French Republican calendar.
Home-page: https://github.com/lakhanmankani/metric-time
Author: Lakhan Mankani
Author-email: lakhan.mankani@gmail.com
License: MIT
Keywords: time,metric
Platform: UNKNOWN
Classifier: Development Status :: 5 - Production/Stable
Classifier: Environment :: Console
Classifier: Intended Audience :: End Users/Desktop
Classifier: License :: OSI Approved :: MIT License
Classifier: Operating System :: OS Independent
Classifier: Programming Language :: Python :: 3 :: Only
Classifier: Programming Language :: Python :: 3
Classifier: Programming Language :: Python :: 3.7
Classifier: Programming Language :: Python :: 3.8
Classifier: Programming Language :: Python :: 3.9
